README.rst
setup.cfg
setup.py
pathlab/__init__.py
pathlab/iso.py
pathlab/rt.py
pathlab/tar.py
pathlab/zip.py
pathlab.egg-info/PKG-INFO
pathlab.egg-info/SOURCES.txt
pathlab.egg-info/dependency_links.txt
pathlab.egg-info/requires.txt
pathlab.egg-info/top_level.txt
pathlab/core/__init__.py
pathlab/core/accessor.py
pathlab/core/creator.py
pathlab/core/path.py
pathlab/core/stat.py