Metadata-Version: 1.2
Name: pathlab
Version: 0.2
Summary: An object-oriented path interface to archives, images, remote filesystems, etc
Home-page: https://github.com/barneygale/pathlab
Author: Barney Gale
Author-email: barney.gale@gmail.com
License: UNKNOWN
Platform: any
Classifier: Development Status :: 3 - Alpha
Classifier: Intended Audience :: Developers
Classifier: License :: OSI Approved :: GNU General Public License v3 (GPLv3)
Classifier: Operating System :: OS Independent
Classifier: Programming Language :: Python
Classifier: Programming Language :: Python :: 3.6
Classifier: Programming Language :: Python :: 3.7
Classifier: Programming Language :: Python :: 3.8
Classifier: Topic :: Software Development :: Libraries :: Python Modules
Requires-Python: >=3.6
